tableautransformer/__init__.py
tableautransformer/backbone.py
tableautransformer/datawrangling.py
tableautransformer-1.0.2.dist-info/LICENCE
tableautransformer-1.0.2.dist-info/METADATA
tableautransformer-1.0.2.dist-info/WHEEL
tableautransformer-1.0.2.dist-info/top_level.txt
tableautransformer-1.0.2.dist-info/RECORD
