Metadata-Version: 2.1
Name: tableautransformer
Version: 1.0.2
Summary: ETL tooling for tableau seed data
Home-page: https://pypi.org/project/tableautransformer
Author: Josh Teixeira
Author-email: jteixeira@cppib.com
License: MIT
Platform: UNKNOWN
Requires-Python: >=3.6
License-File: LICENCE
